silcrow_utils/__init__.py
silcrow_utils/module1.py
silcrow_utils-0.1.1.dist-info/METADATA
silcrow_utils-0.1.1.dist-info/WHEEL
silcrow_utils-0.1.1.dist-info/top_level.txt
silcrow_utils-0.1.1.dist-info/RECORD
